moviequote_generator/__init__.py
moviequote_generator/core.py
moviequote_generator-0.2.0.dist-info/LICENSE
moviequote_generator-0.2.0.dist-info/METADATA
moviequote_generator-0.2.0.dist-info/WHEEL
moviequote_generator-0.2.0.dist-info/top_level.txt
moviequote_generator-0.2.0.dist-info/RECORD
