Metadata-Version: 2.1
Name: moviequote-generator
Version: 0.2.0
Summary: This is a movie quote generator
Home-page: https://github.com/alby2255/moviequote_generator
Author: Albin Biju
Author-email: alby7370@gmail.com
License: UNKNOWN
Platform: UNKNOWN
Classifier: Programming Language :: Python :: 3
Classifier: License :: OSI Approved :: MIT License
Classifier: Operating System :: OS Independent
Requires-Python: >=3.9
